component.py
setup.py
component.egg-info/PKG-INFO
component.egg-info/SOURCES.txt
component.egg-info/dependency_links.txt
component.egg-info/not-zip-safe
component.egg-info/top_level.txt