Metadata-Version: 1.1
Name: component
Version: 0.0.1
Summary: A python library that makes is easy to consume bower components with python.
Home-page: http://github.com/import/component
Author: Daniel Chatfield
Author-email: chatfielddaniel@gmail.com
License: MIT
Platform: UNKNOWN
Classifier: License :: OSI Approved :: MIT License
Classifier: Programming Language :: Python
Classifier: Programming Language :: Python :: 2
Classifier: Programming Language :: Python :: 3
